bneqpri/__init__.py
bneqpri/__main__.py
bneqpri/cli.py
bneqpri/config.py
bneqpri/impl.py
bneqpri/samplers.py
bneqpri/solver/__init__.py
bneqpri/solver/v1.py
bneqpri/solver/v2.py
bneqpri/types.py
bneqpri/utilities.py
bneqpri-0.2.0.dist-info/LICENSE
bneqpri-0.2.0.dist-info/WHEEL
bneqpri-0.2.0.dist-info/METADATA
bneqpri-0.2.0.dist-info/RECORD
