Metadata-Version: 2.1
Name: bneqpri
Version: 0.2.0
Summary: Fixed-Point Methods for Computing Equilibrium Prices
Author: W. Ross Morrow
Author-email: morrowwr@gmail.com
Requires-Python: >=3.9,<4.0
Classifier: Programming Language :: Python :: 3
Classifier: Programming Language :: Python :: 3.10
Classifier: Programming Language :: Python :: 3.9
Requires-Dist: numpy (>=1.23.3,<2.0.0)
